deep_tcn/tcn.py
deep_tcn-0.1.0.dist-info/LICENSE
deep_tcn-0.1.0.dist-info/METADATA
deep_tcn-0.1.0.dist-info/WHEEL
deep_tcn-0.1.0.dist-info/RECORD
