Metadata-Version: 2.1
Name: deep-tcn
Version: 0.1.0
Summary: 
Author: iivek
Author-email: @iivek
Requires-Python: >=3.8,<4.0
Classifier: Programming Language :: Python :: 3
Classifier: Programming Language :: Python :: 3.8
Classifier: Programming Language :: Python :: 3.9
Classifier: Programming Language :: Python :: 3.10
Classifier: Programming Language :: Python :: 3.11
Classifier: Programming Language :: Python :: 3.12
Provides-Extra: examples
Requires-Dist: matplotlib (>=3.0.0) ; extra == "examples"
Requires-Dist: numpy (>=1.17.2)
Requires-Dist: pytorch-lightning (>=1.5.0) ; extra == "examples"
Requires-Dist: torch (>=1.12.1)
